{"symbol": "FTV", "companyName": "Fortive Corp", "exchange": "NEW YORK STOCK EXCHANGE, INC.", "industry": "Iron and Steel Forging ", "website": "www.fortive.com", "description": "Fortive is a provider of essential technologies for connected workflow solutions across a range of attractive end-markets. The company holds leading positions in intelligent operating solutions, precision technologies, and advanced healthcare solutions. Fortive is headquartered in Everett, Washington and employs a team of more than 17,000 research and development, manufacturing, sales, distribution, service and administrative employees in more than 50 countries around the world. With a culture rooted in continuous improvement, the core of our company\u2019s operating model is the Fortive Business System.", "CEO": "James Lico", "securityName": "Fortive Corp", "issueType": "cs", "sector": "Manufacturing", "primarySicCode": 3823, "employees": 17000, "tags": ["Electronic Technology", "Electronic Equipment/Instruments", "Manufacturing", "Iron and Steel Forging "], "address": "6920 Seaway Blvd", "address2": null, "state": "Washington", "city": "Everett", "zip": "98203-5829", "country": "United States", "phone": "14254465000"}