{"symbol": "IPGP", "companyName": "IPG Photonics Corp", "exchange": "NASDAQ/NGS (GLOBAL SELECT MARKET)", "industry": "Semiconductor and Related Device Manufacturing ", "website": "www.ipgphotonics.com", "description": "IPG Photonics Corporation is the leader in high-power \ufffdber lasers and ampli\ufffders used primarily in materials processing and other diverse applications. The Company's mission is to make its \ufffdber laser technology the tool of choice in mass production. IPG accomplishes this mission by delivering superior performance, reliability and usability at a lower total cost of ownership compared with other types of lasers and non-laser tools, allowing end users to increase productivity and decrease costs. A member of the S&P 500\u00ae Index, IPG is headquartered in Oxford, Massachusetts and has more than 25 facilities worldwide.", "CEO": "Valentin Gapontsev", "securityName": "IPG Photonics Corp", "issueType": "cs", "sector": "Manufacturing", "primarySicCode": 3674, "employees": 6060, "tags": ["Electronic Technology", "Electronic Equipment/Instruments", "Semiconductors", "Manufacturing", "Semiconductor and Related Device Manufacturing "], "address": "50 Old Webster Rd", "address2": null, "state": "Massachusetts", "city": "Oxford", "zip": "01540-2706", "country": "US", "phone": "15083731100"}