{"symbol": "IVZ", "companyName": "Invesco Ltd", "exchange": "NEW YORK STOCK EXCHANGE, INC.", "industry": "Securities and Commodity Exchanges", "website": "www.invesco.com", "description": "Invesco Ltd. is a global independent investment management firm dedicated to delivering an investment experience that helps people get more out of life. With offices in more than 20 countries, our distinctive investment teams deliver a comprehensive range of active, passive and alternative investment capabilities. Invesco managed US $1.35 trillion in assets on behalf of clients worldwide as of December 31, 2020.", "CEO": "Martin Flanagan", "securityName": "Invesco Ltd", "issueType": "cs", "sector": "Finance and Insurance", "primarySicCode": 6282, "employees": 8512, "tags": ["Finance", "Investment Managers", "Finance and Insurance", "Securities and Commodity Exchanges"], "address": "1555 Peachtree St NE Ste 1800", "address2": null, "state": "Georgia", "city": "Atlanta", "zip": "30309-2499", "country": "United States", "phone": "14048920896"}