{"symbol": "MET", "companyName": "Metlife Inc", "exchange": "NEW YORK STOCK EXCHANGE, INC.", "industry": "Direct Life Insurance Carriers ", "website": "www.metlife.com", "description": "MetLife, Inc., through its subsidiaries and affiliates ('MetLife'), is one of the world's leading financial services companies, providing insurance, annuities, employee benefits and asset management to help its individual and institutional customers navigate their changing world. Founded in 1868, MetLife has operations in more than 40 markets globally and holds leading positions in the United States, Japan, Latin America, Asia, Europe and the Middle East.", "CEO": "Michel Khalaf", "securityName": "Metlife Inc", "issueType": "cs", "sector": "Finance and Insurance", "primarySicCode": 6311, "employees": 46500, "tags": ["Finance", "Life/Health Insurance", "Multi-Line Insurance", "Finance and Insurance", "Direct Life Insurance Carriers "], "address": "200 Park Ave", "address2": null, "state": "New York", "city": "New York", "zip": "10166-0005", "country": "US", "phone": "12125785500"}