{"symbol": "REG", "companyName": "Regency Centers Corporation", "exchange": "NASDAQ/NGS (GLOBAL SELECT MARKET)", "industry": "Other Financial Vehicles ", "website": "www.regencycenters.com", "description": "Regency Centers is the preeminent national owner, operator, and developer of shopping centers located in affluent, infill suburban trade areas. Its portfolio includes thriving properties merchandised with highly productive grocers, restaurants, service providers, and best-in-class retailers that connect to their neighborhoods, communities, and customers. Operating as a fully integrated real estate company, Regency Centers is a qualified real estate investment trust that is self-administered, self-managed, and an S&P 500 Index member.", "CEO": "Lisa Palmer", "securityName": "Regency Centers Corporation", "issueType": "cs", "sector": "Finance and Insurance", "primarySicCode": 6798, "employees": null, "tags": ["Finance", "Real Estate Investment Trusts", "Finance and Insurance", "Other Financial Vehicles "], "address": "1 Independent Dr Ste 114", "address2": null, "state": "Florida", "city": "Jacksonville", "zip": "32202-5005", "country": "US", "phone": "19045987000"}